rtl/dmem.v
module dmem (
    input clk,
    input we,
    input [31:0] addr,
    input [31:0] wd,
    output [31:0] rd
);
    reg [31:0] memory [0:255];

    integer i;
    initial begin
        for(i = 0; i<256; i++)
            memory[i] = 32'b0;
    end

    assign rd = memory[addr >> 2];

    always @(posedge clk) begin
        if(we)
            memory[addr >> 2] <= wd;
    end

endmodule

rtl/alu.v
module alu (
    input [31:0] a, b,
    input [2:0] op,
    output reg [31:0] result
);
    always @(*) begin
        case (op)
            3'b000: result = a + b;
            3'b001: result = a - b;
            3'b010: result = a & b;
            3'b011: result = a | b;
            default: result = 0; 
        endcase
    end            
endmodule

rtl/regfile.v
module regfile (
    input clk,
    input we,
    input [4:0] rs1, rs2, rd,
    input [31:0] wd,
    output [31:0] rd1, rd2
);
    reg [31:0] regs [0:31];

    integer i;
    initial begin
        for(i=0; i<32; i++)
            regs[i] = 32'b0; 
    end
    
    assign rd1 = regs[rs1];
    assign rd2 = regs[rs2];

    always @(posedge clk) begin
        if(we && rd != 0)
            regs[rd] <= wd; 
    end
endmodule

rtl/cu.v
module cu (
    input  [5:0] opcode,

    output reg reg_write,
    output reg reg_dst, //0 = rd from I-type, 1 = rd from R-type
    output reg alu_src, //0 = rs2, 1 = immediate

    output reg [2:0] alu_op,

    output reg mem_write,
    output reg mem_read,
    output reg mem_to_reg, //1 = load result, 0 = ALU result

    output reg branch
);
    localparam ADD  = 6'b000000;
    localparam SUB  = 6'b000001;
    localparam AND_ = 6'b000010;
    localparam OR_  = 6'b000011;

    localparam ADDI = 6'b000100;
    localparam LW   = 6'b000101;
    localparam SW   = 6'b000110;

    localparam BEQ  = 6'b000111;

    always @(*) begin
        case (opcode)
            ADD: begin
                reg_write = 1;
                reg_dst = 1;
                alu_src = 0;
                alu_op = 3'b000;
                mem_write = 0;
                mem_read = 0;
                mem_to_reg = 0;
                branch = 0;
            end

            SUB: begin
                reg_write = 1;
                reg_dst = 1;
                alu_src = 0;
                alu_op = 3'b001;
                mem_write = 0;
                mem_read = 0;
                mem_to_reg = 0;
                branch = 0;
            end

            AND_: begin
                reg_write = 1;
                reg_dst = 1;
                alu_src = 0;
                alu_op = 3'b010;
                mem_write = 0;
                mem_read = 0;
                mem_to_reg = 0;
                branch = 0;
            end

            OR_: begin
                reg_write = 1;
                reg_dst = 1;
                alu_src = 0;
                alu_op = 3'b011;
                mem_write = 0;
                mem_read = 0;
                mem_to_reg = 0;
                branch = 0;
            end

            ADDI: begin
                reg_write = 1;
                reg_dst = 0;
                alu_src = 1;
                alu_op = 3'b000;
                mem_write = 0;
                mem_read = 0;
                mem_to_reg = 0;
                branch = 0;
            end

            LW: begin
                reg_write = 1;
                reg_dst = 0;
                alu_src = 1;
                alu_op = 3'b000;
                mem_write = 0;
                mem_read = 1;
                mem_to_reg = 1;
                branch = 0;
            end

            SW: begin
                reg_write = 0;
                reg_dst = 0; // Don't care
                alu_src = 1;
                alu_op = 3'b000;
                mem_write = 1;
                mem_read = 0;
                mem_to_reg = 0; // Don't care
                branch = 0;
            end

            BEQ: begin
                reg_write = 0;
                reg_dst = 0; // Don't care
                alu_src = 0;
                alu_op = 3'b001; // SUB for comparison
                mem_write = 0;
                mem_read = 0;
                mem_to_reg = 0; // Don't care
                branch = 1;
            end

            default: begin
                reg_write = 0;
                reg_dst = 0;
                alu_src = 0;
                alu_op = 3'b000;
                mem_write = 0;
                mem_read = 0;
                mem_to_reg = 0;
                branch = 0;
            end

        endcase
    end
    
endmodule

rtl/imem.v
module imem (
    input [31:0] addr,
    output [31:0] instr
);
    reg [31:0] memory [0:255];
    
    initial begin
        $readmemh("program.mem", memory);
    end

    assign instr = memory[addr >> 2];
endmodule

rtl/pc.v
module pc (
    input clk,
    input reset,
    input [31:0] next_pc,
    output reg[31:0] pc
);
    always @(posedge clk or posedge reset) begin
        if(reset)
            pc <= 0;
        else
            pc <= next_pc;
    end

endmodule

rtl/cpu.v
module cpu (
    input clk,
    input reset
);
    // INTERNAL WIRES

    wire [31:0] pc, next_pc;

    wire [31:0] instr;

    wire [5:0] opcode;
    wire [4:0] rs1, rs2, rd;
    wire [15:0] imm;

    wire [31:0] reg_data1, reg_data2;
    wire [4:0] write_reg;
    wire [31:0] write_data;

    wire [31:0] alu_in2;
    wire [31:0] alu_result;

    wire [31:0] mem_data;

    wire reg_write, reg_dst, alu_src;
    wire [2:0] alu_op;
    wire mem_write, mem_read, mem_to_reg;
    wire branch;

    wire [31:0] imm_ext;
    
    wire branch_taken;

    //INSTRUCTION DECODE

    assign opcode = instr[31:26];
    assign rs1 = instr[25:21];
    assign rs2 = instr[20:16];
    assign rd  = instr[15:11];
    assign imm = instr[15:0];

    //MODULE INSTANTIATIONS

    pc pc_inst (
        .clk(clk),
        .reset(reset),
        .next_pc(next_pc),
        .pc(pc)
    );

    imem imem_inst (
        .addr(pc),
        .instr(instr)
    );

    cu cu_inst (
        .opcode(opcode),
        .reg_write(reg_write),
        .reg_dst(reg_dst),
        .alu_src(alu_src),
        .alu_op(alu_op),
        .mem_write(mem_write),
        .mem_read(mem_read),
        .mem_to_reg(mem_to_reg),
        .branch(branch)
    );

    assign write_reg = reg_dst ? rd : rs2;

    regfile regfile_inst (
        .clk(clk),
        .we(reg_write),
        .rs1(rs1),
        .rs2(rs2),
        .rd(write_reg),
        .wd(write_data),
        .rd1(reg_data1),
        .rd2(reg_data2)
    );

    assign imm_ext = {{16{imm[15]}}, imm};

    assign alu_in2 = alu_src ? imm_ext : reg_data2;

    alu alu_inst (
        .a(reg_data1),
        .b(alu_in2),
        .op(alu_op),
        .result(alu_result)
    );

    dmem dmem_inst (
        .clk(clk),
        .we(mem_write),
        .addr(alu_result),
        .wd(reg_data2),
        .rd(mem_data)
    );

    assign write_data = mem_to_reg ? mem_data : alu_result;

    assign branch_taken = branch & (alu_result == 0);

    assign next_pc = branch_taken ? (pc + (imm_ext << 2)) : (pc+4);

endmodule

tb/cpu_tb.v
`timescale 1ns/1ps

module cpu_tb;

    reg clk;
    reg reset;

    // Instantiate CPU
    cpu uut (
        .clk(clk),
        .reset(reset)
    );

    // Clock generation
    always #5 clk = ~clk; // 10ns period

    initial begin
        $monitor("Time=%0t PC=%h", $time, uut.pc);
    end

    initial begin
        // Dump waveform
        $dumpfile("sim/cpu.vcd");
        $dumpvars(0, cpu_tb);

        // Init
        clk = 0;
        reset = 1;

        // Reset pulse
        #10;
        reset = 0;

        // Run simulation
        #100;

        // Finish
        $finish;
    end

endmodule

sim/cpu.vcd
$date
	Wed Apr  1 01:01:14 2026
$end
$version
	Icarus Verilog
$end
$timescale
	1ps
$end
$scope module cpu_tb $end
$var reg 1 ! clk $end
$var reg 1 " reset $end
$scope module uut $end
$var wire 1 # branch_taken $end
$var wire 1 ! clk $end
$var wire 1 " reset $end
$var wire 5 $ write_reg [4:0] $end
$var wire 32 % write_data [31:0] $end
$var wire 5 & rs2 [4:0] $end
$var wire 5 ' rs1 [4:0] $end
$var wire 1 ( reg_write $end
$var wire 1 ) reg_dst $end
$var wire 32 * reg_data2 [31:0] $end
$var wire 32 + reg_data1 [31:0] $end
$var wire 5 , rd [4:0] $end
$var wire 32 - pc [31:0] $end
$var wire 6 . opcode [5:0] $end
$var wire 32 / next_pc [31:0] $end
$var wire 1 0 mem_write $end
$var wire 1 1 mem_to_reg $end
$var wire 1 2 mem_read $end
$var wire 32 3 mem_data [31:0] $end
$var wire 32 4 instr [31:0] $end
$var wire 32 5 imm_ext [31:0] $end
$var wire 16 6 imm [15:0] $end
$var wire 1 7 branch $end
$var wire 1 8 alu_src $end
$var wire 32 9 alu_result [31:0] $end
$var wire 3 : alu_op [2:0] $end
$var wire 32 ; alu_in2 [31:0] $end
$scope module alu_inst $end
$var wire 32 < b [31:0] $end
$var wire 3 = op [2:0] $end
$var wire 32 > a [31:0] $end
$var reg 32 ? result [31:0] $end
$upscope $end
$scope module cu_inst $end
$var wire 6 @ opcode [5:0] $end
$var parameter 6 A ADD $end
$var parameter 6 B ADDI $end
$var parameter 6 C AND_ $end
$var parameter 6 D BEQ $end
$var parameter 6 E LW $end
$var parameter 6 F OR_ $end
$var parameter 6 G SUB $end
$var parameter 6 H SW $end
$var reg 3 I alu_op [2:0] $end
$var reg 1 8 alu_src $end
$var reg 1 7 branch $end
$var reg 1 2 mem_read $end
$var reg 1 1 mem_to_reg $end
$var reg 1 0 mem_write $end
$var reg 1 ) reg_dst $end
$var reg 1 ( reg_write $end
$upscope $end
$scope module dmem_inst $end
$var wire 32 J addr [31:0] $end
$var wire 1 ! clk $end
$var wire 32 K rd [31:0] $end
$var wire 1 0 we $end
$var wire 32 L wd [31:0] $end
$var integer 32 M i [31:0] $end
$upscope $end
$scope module imem_inst $end
$var wire 32 N instr [31:0] $end
$var wire 32 O addr [31:0] $end
$upscope $end
$scope module pc_inst $end
$var wire 1 ! clk $end
$var wire 32 P next_pc [31:0] $end
$var wire 1 " reset $end
$var reg 32 Q pc [31:0] $end
$upscope $end
$scope module regfile_inst $end
$var wire 1 ! clk $end
$var wire 5 R rd [4:0] $end
$var wire 32 S rd1 [31:0] $end
$var wire 32 T rd2 [31:0] $end
$var wire 5 U rs1 [4:0] $end
$var wire 5 V rs2 [4:0] $end
$var wire 32 W wd [31:0] $end
$var wire 1 ( we $end
$var integer 32 X i [31:0] $end
$upscope $end
$upscope $end
$upscope $end
$enddefinitions $end
$comment Show the parameter values. $end
$dumpall
b110 H
b1 G
b11 F
b101 E
b111 D
b10 C
b100 B
b0 A
$end
#0
$dumpvars
b100000 X
b101 W
b1 V
b0 U
b0 T
b0 S
b1 R
b0 Q
b100 P
b0 O
b10000000000010000000000000101 N
b100000000 M
b0 L
b0 K
b101 J
b0 I
b100 @
b101 ?
b0 >
b0 =
b101 <
b101 ;
b0 :
b101 9
18
07
b101 6
b101 5
b10000000000010000000000000101 4
b0 3
02
01
00
b100 /
b100 .
b0 -
b0 ,
b0 +
b0 *
0)
1(
b0 '
b1 &
b101 %
b1 $
0#
1"
0!
$end
#5000
b101 *
b101 L
b101 T
1!
#10000
0!
0"
#15000
b1010 %
b1010 W
b1010 9
b1010 ?
b1010 J
b1010 ;
b1010 <
b10 $
b10 R
b1010 5
b1010 6
b0 *
b0 L
b0 T
b10 &
b10 V
b10000000000100000000000001010 4
b10000000000100000000000001010 N
b1000 /
b1000 P
b100 -
b100 O
b100 Q
1!
#20000
0!
#25000
b1111 %
b1111 W
b11 $
b11 R
b1111 9
b1111 ?
b1111 J
08
1)
b1100000000000 5
b1100000000000 6
b11 ,
b101 +
b101 >
b101 S
b1 '
b1 U
b0 .
b0 @
b1000100001100000000000 4
b1000100001100000000000 N
b1100 /
b1100 P
b1010 *
b1010 L
b1010 T
b1000 -
b1000 O
b1000 Q
1!
#30000
0!
#35000
b0 %
b0 W
b0 $
b0 R
b0 ;
b0 <
b0 9
b0 ?
b0 J
b0 5
b0 6
b0 ,
b0 *
b0 L
b0 T
b0 &
b0 V
b0 +
b0 >
b0 S
b0 '
b0 U
b0 4
b0 N
b10000 /
b10000 P
b1100 -
b1100 O
b1100 Q
1!
#40000
0!
#45000
b10100 /
b10100 P
b10000 -
b10000 O
b10000 Q
1!
#50000
0!
#55000
b11000 /
b11000 P
b10100 -
b10100 O
b10100 Q
1!
#60000
0!
#65000
b11100 /
b11100 P
b11000 -
b11000 O
b11000 Q
1!
#70000
0!
#75000
b100000 /
b100000 P
b11100 -
b11100 O
b11100 Q
1!
#80000
0!
#85000
b100100 /
b100100 P
b100000 -
b100000 O
b100000 Q
1!
#90000
0!
#95000
b101000 /
b101000 P
b100100 -
b100100 O
b100100 Q
1!
#100000
0!
#105000
b101100 /
b101100 P
b101000 -
b101000 O
b101000 Q
1!
