rtl/cu.v
module cu (
    input  [5:0] opcode,

    output reg reg_write,
    output reg reg_dst, //0 = rd from I-type, 1 = rd from R-type
    output reg alu_src, //0 = rs2, 1 = immediate

    output reg [2:0] alu_op,

    output reg mem_write,
    output reg mem_read,
    output reg mem_to_reg, //1 = load result, 0 = ALU result

    output reg branch
);
    localparam ADD  = 6'b000000;
    localparam SUB  = 6'b000001;
    localparam AND_ = 6'b000010;
    localparam OR_  = 6'b000011;

    localparam ADDI = 6'b000100;
    localparam LW   = 6'b000101;
    localparam SW   = 6'b000110;

    localparam BEQ  = 6'b000111;

    always @(*) begin
        case (opcode)
            ADD: begin
                reg_write = 1;
                reg_dst = 1;
                alu_src = 0;
                alu_op = 3'b000;
                mem_write = 0;
                mem_read = 0;
                mem_to_reg = 0;
                branch = 0;
            end

            SUB: begin
                reg_write = 1;
                reg_dst = 1;
                alu_src = 0;
                alu_op = 3'b001;
                mem_write = 0;
                mem_read = 0;
                mem_to_reg = 0;
                branch = 0;
            end

            AND_: begin
                reg_write = 1;
                reg_dst = 1;
                alu_src = 0;
                alu_op = 3'b010;
                mem_write = 0;
                mem_read = 0;
                mem_to_reg = 0;
                branch = 0;
            end

            OR_: begin
                reg_write = 1;
                reg_dst = 1;
                alu_src = 0;
                alu_op = 3'b011;
                mem_write = 0;
                mem_read = 0;
                mem_to_reg = 0;
                branch = 0;
            end

            ADDI: begin
                reg_write = 1;
                reg_dst = 0;
                alu_src = 1;
                alu_op = 3'b000;
                mem_write = 0;
                mem_read = 0;
                mem_to_reg = 0;
                branch = 0;
            end

            LW: begin
                reg_write = 1;
                reg_dst = 0;
                alu_src = 1;
                alu_op = 3'b000;
                mem_write = 0;
                mem_read = 1;
                mem_to_reg = 1;
                branch = 0;
            end

            SW: begin
                reg_write = 0;
                reg_dst = 0; // Don't care
                alu_src = 1;
                alu_op = 3'b000;
                mem_write = 1;
                mem_read = 0;
                mem_to_reg = 0; // Don't care
                branch = 0;
            end

            BEQ: begin
                reg_write = 0;
                reg_dst = 0; // Don't care
                alu_src = 0;
                alu_op = 3'b001; // SUB for comparison
                mem_write = 0;
                mem_read = 0;
                mem_to_reg = 0; // Don't care
                branch = 1;
            end

            default: begin
                reg_write = 0;
                reg_dst = 0;
                alu_src = 0;
                alu_op = 3'b000;
                mem_write = 0;
                mem_read = 0;
                mem_to_reg = 0;
                branch = 0;
            end

        endcase
    end
    
endmodule

tb/cu_tb.v
`timescale 1ns/1ps

module cu_tb;

    reg [5:0] opcode;

    wire 
        reg_write,
        reg_dst,
        alu_src,
        mem_write,
        mem_read,
        mem_to_reg,
        branch;
    
    wire [2:0] alu_op;

    cu uut (
        .opcode(opcode),
        .reg_write(reg_write),
        .reg_dst(reg_dst),
        .alu_src(alu_src),
        .alu_op(alu_op),
        .mem_write(mem_write),
        .mem_read(mem_read),
        .mem_to_reg(mem_to_reg),
        .branch(branch)
    );

    initial begin
        $dumpfile("sim/cu.vcd");
        $dumpvars(0, cu_tb);
        
        opcode = 6'b000000; #10; // ADD
        opcode = 6'b000001; #10; // SUB
        opcode = 6'b000010; #10; // AND
        opcode = 6'b000011; #10; // OR
        opcode = 6'b000100; #10; // ADDI
        opcode = 6'b000101; #10; // LW
        opcode = 6'b000110; #10; // SW
        opcode = 6'b000111; #10; // BEQ

        $finish;
    end

endmodule

sim/cu.vcd
$date
	Tue Mar 24 19:56:23 2026
$end
$version
	Icarus Verilog
$end
$timescale
	1ps
$end
$scope module cu_tb $end
$var wire 1 ! reg_write $end
$var wire 1 " reg_dst $end
$var wire 1 # mem_write $end
$var wire 1 $ mem_to_reg $end
$var wire 1 % mem_read $end
$var wire 1 & branch $end
$var wire 1 ' alu_src $end
$var wire 3 ( alu_op [2:0] $end
$var reg 6 ) opcode [5:0] $end
$scope module uut $end
$var wire 6 * opcode [5:0] $end
$var parameter 6 + ADD $end
$var parameter 6 , ADDI $end
$var parameter 6 - AND_ $end
$var parameter 6 . BEQ $end
$var parameter 6 / LW $end
$var parameter 6 0 OR_ $end
$var parameter 6 1 SUB $end
$var parameter 6 2 SW $end
$var reg 3 3 alu_op [2:0] $end
$var reg 1 ' alu_src $end
$var reg 1 & branch $end
$var reg 1 % mem_read $end
$var reg 1 $ mem_to_reg $end
$var reg 1 # mem_write $end
$var reg 1 " reg_dst $end
$var reg 1 ! reg_write $end
$upscope $end
$upscope $end
$enddefinitions $end
$comment Show the parameter values. $end
$dumpall
b110 2
b1 1
b11 0
b101 /
b111 .
b10 -
b100 ,
b0 +
$end
#0
$dumpvars
b0 3
b0 *
b0 )
b0 (
0'
0&
0%
0$
0#
1"
1!
$end
#10000
b1 (
b1 3
b1 )
b1 *
#20000
b10 (
b10 3
b10 )
b10 *
#30000
b11 (
b11 3
b11 )
b11 *
#40000
b0 (
b0 3
1'
0"
b100 )
b100 *
#50000
1$
1%
b101 )
b101 *
#60000
0$
0%
1#
0!
b110 )
b110 *
#70000
1&
0#
b1 (
b1 3
0'
b111 )
b111 *
