rtl/imem.v
module imem (
    input [31:0] addr,
    output [31:0] instr
);
    reg [31:0] memory [0:255];
    
    initial begin
        $readmemh("program.mem", memory);
    end

    assign instr = memory[addr >> 2];
endmodule

tb/imem_tb.v
`timescale 1ns/1ps

module imem_tb;

    reg clk = 1;
    reg [31:0] addr;
    wire [31:0] instr;

    imem imem_inst(.addr(addr), .instr(instr));

    always #5 clk = ~clk;

    initial begin
        $dumpfile("sim/imem.vcd");
        $dumpvars(0, imem_tb);

        addr = 32'h0; #10;
        addr = 32'h4; #10;
        addr = 32'h8; #10;
        addr = 32'hC; #10;
        addr = 32'h10; #10;
        addr = 32'h14; #10;
        addr = 32'h18; #10;
        addr = 32'h1C; #10;

        $finish;
    end
endmodule

sim/imem.vcd
$date
	Tue Mar 24 00:59:02 2026
$end
$version
	Icarus Verilog
$end
$timescale
	1ps
$end
$scope module imem_tb $end
$var wire 32 ! instr [31:0] $end
$var reg 32 " addr [31:0] $end
$var reg 1 # clk $end
$scope module imem_inst $end
$var wire 32 $ addr [31:0] $end
$var wire 32 % instr [31:0] $end
$upscope $end
$upscope $end
$enddefinitions $end
$comment Show the parameter values. $end
$dumpall
$end
#0
$dumpvars
b1010 %
b0 $
1#
b0 "
b1010 !
$end
#5000
0#
#10000
b1 !
b1 %
1#
b100 "
b100 $
#15000
0#
#20000
b1010000000000000 !
b1010000000000000 %
1#
b1000 "
b1000 $
#25000
0#
#30000
b10110000 !
b10110000 %
1#
b1100 "
b1100 $
#35000
0#
#40000
b100000 !
b100000 %
1#
b10000 "
b10000 $
#45000
0#
#50000
b0 !
b0 %
1#
b10100 "
b10100 $
#55000
0#
#60000
1#
b11000 "
b11000 $
#65000
0#
#70000
1#
b11100 "
b11100 $
