rtl/pc.v
module pc (
    input clk,
    input reset,
    input [31:0] next_pc,
    output reg[31:0] pc
);
    always @(posedge clk or posedge reset) begin
        if(reset)
            pc <= 0;
        else
            pc <= next_pc;
    end

endmodule

tb/pc_tb.v
`timescale 1ns/1ps

module pc_tb;
    
    reg clk = 0;
    reg reset = 0;
    reg [31:0] next_pc;
    wire [31:0] pc;

    pc pc_inst(.clk(clk), .reset(reset), .next_pc(next_pc), .pc(pc));

    always #5 clk = ~clk;

    initial begin
        $dumpfile("sim/pc.vcd");
        $dumpvars(0, pc_tb);

        reset = 1; #10;
        reset = 0; next_pc = 32'h4; #10;
        next_pc = 32'h8; #10;
        next_pc = 32'hC; #10;
        next_pc = 32'h10; #10;
        reset = 1; #10;

        $finish;
    end

endmodule

sim/pc.vcd
$date
	Tue Mar 24 19:09:46 2026
$end
$version
	Icarus Verilog
$end
$timescale
	1ps
$end
$scope module pc_tb $end
$var wire 32 ! pc [31:0] $end
$var reg 1 " clk $end
$var reg 32 # next_pc [31:0] $end
$var reg 1 $ reset $end
$scope module pc_inst $end
$var wire 1 " clk $end
$var wire 32 % next_pc [31:0] $end
$var wire 1 $ reset $end
$var reg 32 & pc [31:0] $end
$upscope $end
$upscope $end
$enddefinitions $end
$comment Show the parameter values. $end
$dumpall
$end
#0
$dumpvars
b0 &
bx %
1$
bx #
0"
b0 !
$end
#5000
1"
#10000
0"
b100 #
b100 %
0$
#15000
b100 !
b100 &
1"
#20000
0"
b1000 #
b1000 %
#25000
b1000 !
b1000 &
1"
#30000
0"
b1100 #
b1100 %
#35000
b1100 !
b1100 &
1"
#40000
0"
b10000 #
b10000 %
#45000
b10000 !
b10000 &
1"
#50000
b0 !
b0 &
0"
1$
